notion2pg_bulk/__init__.py
notion2pg_bulk/cli.py
notion2pg_bulk/migrator.py
notion2pg_bulk/progress_tracker.py
notion2pg_bulk/rate_limiter.py
notion2pg_bulk/schema_mapper.py
notion2pg_bulk-0.1.0.dist-info/WHEEL
notion2pg_bulk-0.1.0.dist-info/entry_points.txt
notion2pg_bulk-0.1.0.dist-info/METADATA
notion2pg_bulk-0.1.0.dist-info/RECORD
