Metadata-Version: 2.3
Name: notion2pg-bulk
Version: 0.1.0
Summary: A Python package that automatically finds and migrates to PostgreSQL all databases in a Notion workspace.
Keywords: notion,postgresql,migration,database,export,workspace,notion export,notion migrate
Author: benvigano
License: GPL-3.0-or-later
Classifier: Development Status :: 4 - Beta
Classifier: Intended Audience :: Developers
Classifier: License :: OSI Approved :: GNU General Public License v3 or later (GPLv3+)
Classifier: Programming Language :: Python :: 3
Classifier: Programming Language :: Python :: 3.8
Classifier: Programming Language :: Python :: 3.9
Classifier: Programming Language :: Python :: 3.10
Classifier: Programming Language :: Python :: 3.11
Classifier: Programming Language :: Python :: 3.12
Classifier: Topic :: Database
Classifier: Topic :: Software Development :: Libraries :: Python Modules
Requires-Dist: notion-client>=2.2.1
Requires-Dist: psycopg2-binary>=2.9.5
Requires-Dist: sqlalchemy>=2.0.0
Requires-Dist: tabulate>=0.9.0
Requires-Dist: tqdm>=4.64.0
Requires-Python: >=3.8
Project-URL: Homepage, https://github.com/benvigano/notion2pg-bulk
Project-URL: Issues, https://github.com/benvigano/notion2pg-bulk/issues
Project-URL: Repository, https://github.com/benvigano/notion2pg-bulk
